hmmconf/__init__.py
hmmconf/analysis.py
hmmconf/base.py
hmmconf/base_utils.py
hmmconf/conform.py
hmmconf/example_data.py
hmmconf/hmmconf_setup.py
hmmconf/metric.py
hmmconf/model.py
hmmconf/numba_utils.py
hmmconf/pm_extra.py
hmmconf/preprocess.py
hmmconf/tracker.py
hmmconf/utils.py
hmmconf/visualize.py
hospital-billing/__init__.py
hospital-billing/experiment.py
tests/__init__.py
tests/conftest.py
tests/test_base.py
tests/test_conform.py
tests/test_hmmconf_setup.py
tests/test_numba_utils.py
tests/test_preprocess.py
tests/test_utils.py
tests/utils.py
hmmconf-2.0.0.dist-info/LICENSE
hmmconf-2.0.0.dist-info/METADATA
hmmconf-2.0.0.dist-info/WHEEL
hmmconf-2.0.0.dist-info/top_level.txt
hmmconf-2.0.0.dist-info/RECORD
