Metadata-Version: 2.1
Name: hmmconf
Version: 2.0.0
Summary: HMM-based conformance checker
Home-page: UNKNOWN
Author: Wai Lam Jonathan Lee
Author-email: walee@uc.cl
License: UNKNOWN
Platform: UNKNOWN
Requires-Dist: icc-rt
Requires-Dist: numba
Requires-Dist: numpy
Requires-Dist: pm4py
